jinjax/__init__.py
jinjax/catalog.py
jinjax/component.py
jinjax/exceptions.py
jinjax/html_attrs.py
jinjax/jinjax.py
jinjax/middleware.py
jinjax/py.typed
jinjax/utils.py
jinjax-0.63.dist-info/METADATA
jinjax-0.63.dist-info/WHEEL
jinjax-0.63.dist-info/top_level.txt
jinjax-0.63.dist-info/RECORD
