Metadata-Version: 2.4
Name: jinjax
Version: 0.63
Summary: Replace your HTML templates with Python server-Side components
Author-email: Juan Pablo Scaletti <juanpablo@jpscaletti.com>
License: MIT License
Project-URL: homepage, https://jinjax.scaletti.dev/
Project-URL: repository, https://github.com/jpsca/jinjax
Project-URL: documentation, https://jinjax.scaletti.dev/guides/
Classifier: Development Status :: 4 - Beta
Classifier: Environment :: Web Environment
Classifier: Intended Audience :: Developers
Classifier: Programming Language :: Python :: 3 :: Only
Classifier: Programming Language :: Python :: 3.11
Classifier: Programming Language :: Python :: 3.12
Classifier: Programming Language :: Python :: 3.13
Classifier: Topic :: Internet :: WWW/HTTP :: Dynamic Content
Classifier: Topic :: Software Development :: Libraries
Classifier: Topic :: Software Development :: Libraries :: Python Modules
Classifier: Topic :: Software Development :: User Interfaces
Classifier: Topic :: Text Processing :: Markup :: HTML
Classifier: Typing :: Typed
Requires-Python: <4,>=3.11
Requires-Dist: jinja2>=3.0
Requires-Dist: markupsafe>=2.0
Provides-Extra: whitenoise
Requires-Dist: whitenoise~=6.9.0; extra == "whitenoise"
